pylava_pylint/__init__.py
pylava_pylint/main.py
pylava_pylint/pylint.rc
pylava_pylint-0.0.3.dist-info/METADATA
pylava_pylint-0.0.3.dist-info/RECORD
pylava_pylint-0.0.3.dist-info/WHEEL
pylava_pylint-0.0.3.dist-info/entry_points.txt
pylava_pylint-0.0.3.dist-info/top_level.txt
