Metadata-Version: 2.1
Name: pylava-pylint
Version: 0.0.3
Summary: Pylint integration to pylava library.
Home-page: http://github.com/pylava/pylava_pylint
Maintainer: Susam Pal
Maintainer-email: susam@susam.in
License: MIT
Platform: Any
Classifier: Intended Audience :: Developers
Classifier: License :: OSI Approved :: MIT License
Classifier: Operating System :: OS Independent
Classifier: Programming Language :: Python
Requires-Dist: pylava (>=0.0.1)
Requires-Dist: pylint (>=1.6.4)
